esy/__init__.py
esy/auth.py
esy/client.py
esy/constants.py
esy/devel.py
esy/entities.py
esy/exceptions.py
esy-1.2.0.dist-info/METADATA
esy-1.2.0.dist-info/RECORD
esy-1.2.0.dist-info/WHEEL
esy-1.2.0.dist-info/top_level.txt
