Metadata-Version: 2.1
Name: esy
Version: 1.2.0
Summary: ESY is an ESI wrapper aiming to be simple and pythonic.
Home-page: https://github.com/kriberg/esy.git
Author: Kristian Berg
Author-email: eve.vittoros@gmail.com
License: MIT
Platform: UNKNOWN
Classifier: License :: OSI Approved :: GNU Lesser General Public License v3 (LGPLv3)
Classifier: Development Status :: 4 - Beta
Classifier: Programming Language :: Python
Classifier: Programming Language :: Python :: 3
Classifier: Programming Language :: Python :: 3.6
Classifier: Programming Language :: Python :: Implementation :: CPython
Classifier: Topic :: Games/Entertainment
Requires-Python: >=3.6.0
